rdillib/__init__.py
rdillib-0.0.1.dist-info/METADATA
rdillib-0.0.1.dist-info/WHEEL
rdillib-0.0.1.dist-info/top_level.txt
rdillib-0.0.1.dist-info/RECORD
